AUTHORS.txt
CHANGES.txt
LICENSE.txt
MANIFEST.in
README.rst
setup.cfg
setup.py
docs/Makefile
docs/__init__.py
docs/conf.py
docs/configuration.rst
docs/cookbook.rst
docs/development.rst
docs/index.rst
docs/installing.rst
docs/logic.rst
docs/make.bat
docs/news.rst
docs/pipext.py
docs/quickstart.rst
docs/usage.rst
docs/user_guide.rst
docs/reference/index.rst
docs/reference/pip.rst
docs/reference/pip_download.rst
docs/reference/pip_freeze.rst
docs/reference/pip_hash.rst
docs/reference/pip_install.rst
docs/reference/pip_list.rst
docs/reference/pip_search.rst
docs/reference/pip_show.rst
docs/reference/pip_uninstall.rst
docs/reference/pip_wheel.rst
pip/__init__.py
pip/__main__.py
pip/basecommand.py
pip/baseparser.py
pip/cmdoptions.py
pip/download.py
pip/exceptions.py
pip/index.py
pip/locations.py
pip/pep425tags.py
pip/status_codes.py
pip/wheel.py
pip/_vendor/README.rst
pip/_vendor/__init__.py
pip/_vendor/ipaddress.py
pip/_vendor/pyparsing.py
pip/_vendor/re-vendor.py
pip/_vendor/retrying.py
pip/_vendor/six.py
pip/_vendor/vendor.txt
pip/_vendor/cachecontrol/__init__.py
pip/_vendor/cachecontrol/_cmd.py
pip/_vendor/cachecontrol/adapter.py
pip/_vendor/cachecontrol/cache.py
pip/_vendor/cachecontrol/compat.py
pip/_vendor/cachecontrol/controller.py
pip/_vendor/cachecontrol/filewrapper.py
pip/_vendor/cachecontrol/heuristics.py
pip/_vendor/cachecontrol/serialize.py
pip/_vendor/cachecontrol/wrapper.py
pip/_vendor/cachecontrol/caches/__init__.py
pip/_vendor/cachecontrol/caches/file_cache.py
pip/_vendor/cachecontrol/caches/redis_cache.py
pip/_vendor/colorama/__init__.py
pip/_vendor/colorama/ansi.py
pip/_vendor/colorama/ansitowin32.py
pip/_vendor/colorama/initialise.py
pip/_vendor/colorama/win32.py
pip/_vendor/colorama/winterm.py
pip/_vendor/distlib/__init__.py
pip/_vendor/distlib/compat.py
pip/_vendor/distlib/database.py
pip/_vendor/distlib/index.py
pip/_vendor/distlib/locators.py
pip/_vendor/distlib/manifest.py
pip/_vendor/distlib/markers.py
pip/_vendor/distlib/metadata.py
sl_pip.egg-info/PKG-INFO
sl_pip.egg-info/SOURCES.txt
sl_pip.egg-info/dependency_links.txt
sl_pip.egg-info/entry_points.txt
sl_pip.egg-info/not-zip-safe
sl_pip.egg-info/requires.txt
sl_pip.egg-info/top_level.txt