Metadata-Version: 1.1
Name: sl-pip
Version: 8.2.1
Summary: A Custom fork of pip
Home-page: https://pip.pypa.io/
Author: The pip developers
Author-email: python-virtualenv@groups.google.com
License: MIT
Keywords: easy_install distutils setuptools egg virtualenv
Platform: UNKNOWN
Classifier: Development Status :: 5 - Production/Stable
Classifier: Intended Audience :: Developers
Classifier: License :: OSI Approved :: MIT License
Classifier: Topic :: Software Development :: Build Tools
Classifier: Programming Language :: Python :: 2
Classifier: Programming Language :: Python :: 2.6
Classifier: Programming Language :: Python :: 2.7
Classifier: Programming Language :: Python :: 3
Classifier: Programming Language :: Python :: 3.3
Classifier: Programming Language :: Python :: 3.4
Classifier: Programming Language :: Python :: 3.5
Classifier: Programming Language :: Python :: Implementation :: PyPy
